{"pathToFile":"../sermon-outlines-by-stephen-reynolds-sr/20140831A.txt","fileName":"20140831A.txt","type":".txt","link":"https://githubusercontent.com/raw/sermon-outlines-by-stephen-reynolds-sr/20140831A.txt","uuid":271,"content":"2 Corinthians 5:17\r\nTherefore if any man be in Christ, he is a new creature: old things are passed away; behold, all things are become new. \r\n\r\n\r\nThe Lordship of Christ and Servanthood of the Believer\r\n2Co 5:5 Now he that hath wrought us for the selfsame thing is God, who also hath given unto us the earnest of the Spirit. \r\n\r\nTo become a servant we must first be born again.\r\n\r\nclip < ~/.ssh/id_rsa.pub"}